revonto/__init__.py
revonto/associations.py
revonto/geneinfo.py
revonto/multiple_testing.py
revonto/ontology.py
revonto/ortholog.py
revonto/pvalcalc.py
revonto/reverse_lookup.py
revonto/utils.py
revonto-0.3.0.dist-info/LICENSE
revonto-0.3.0.dist-info/METADATA
revonto-0.3.0.dist-info/WHEEL
revonto-0.3.0.dist-info/top_level.txt
revonto-0.3.0.dist-info/RECORD
