Metadata-Version: 2.1
Name: revonto
Version: 0.3.0
Summary: Python library for Gene Ontology Reverse Lookup
Author-email: Vladimir Smrkolj <vladimir.smrkolj@gmail.com>, Aljoša Škorjanc <skorjanc.aljosa@gmail.com>
License: GPL-3.0 License
Keywords: gene ontology,reverse lookup
Classifier: Development Status :: 3 - Alpha
Classifier: Intended Audience :: Science/Research
Classifier: License :: OSI Approved :: GNU General Public License v3 or later (GPLv3+)
Classifier: Programming Language :: Python :: 3
Classifier: Topic :: Scientific/Engineering :: Bio-Informatics
Requires-Python: >=3.9
License-File: LICENSE
Requires-Dist: numpy
Requires-Dist: scipy
Requires-Dist: statsmodels
Requires-Dist: requests
Provides-Extra: lint
Requires-Dist: ruff ; extra == 'lint'
Requires-Dist: black ; extra == 'lint'
Requires-Dist: mypy ; extra == 'lint'
Requires-Dist: check-manifest ; extra == 'lint'
Requires-Dist: isort ; extra == 'lint'
Provides-Extra: test
Requires-Dist: pytest ; extra == 'test'
Requires-Dist: pytest-cov ; extra == 'test'
Requires-Dist: pytest-sugar ; extra == 'test'
